textarena/__init__.py
textarena/api.py
textarena/core.py
textarena/state.py
textarena/agents/__init__.py
textarena/agents/basic_agents.py
textarena/agents/wrappers.py
textarena/envs/__init__.py
textarena/envs/registration.py
textarena/envs/Alquerque/__init__.py
textarena/envs/Alquerque/env.py
textarena/envs/BabyAiText/env.py
textarena/envs/BabyAiText/tests.py
textarena/envs/Bandit/__init__.py
textarena/envs/Bandit/env.py
textarena/envs/Battleship/__init__.py
textarena/envs/Battleship/env.py
textarena/envs/Battleship/renderer.py
textarena/envs/Blackjack/__init__.py
textarena/envs/Blackjack/env.py
textarena/envs/BlindAuction/__init__.py
textarena/envs/BlindAuction/env.py
textarena/envs/BlindAuction/renderer.py
textarena/envs/Breakthrough/__init__.py
textarena/envs/Breakthrough/env.py
textarena/envs/Breakthrough/renderer.py
textarena/envs/Briscola/__init__.py
textarena/envs/Briscola/env.py
textarena/envs/CharacterConclave/__init__.py
textarena/envs/CharacterConclave/env.py
textarena/envs/CharacterConclave/renderer.py
textarena/envs/Checkers/__init__.py
textarena/envs/Checkers/env.py
textarena/envs/Checkers/renderer.py
textarena/envs/Chess/__init__.py
textarena/envs/Chess/env.py
textarena/envs/Chess/renderer.py
textarena/envs/Chopsticks/__init__.py
textarena/envs/Chopsticks/env.py
textarena/envs/Chopsticks/renderer.py
textarena/envs/Codenames/__init__.py
textarena/envs/Codenames/env.py
textarena/envs/ColonelBlotto/env.py
textarena/envs/ColonelBlotto/renderer.py
textarena/envs/ConnectFour/__init__.py
textarena/envs/ConnectFour/env.py
textarena/envs/ConnectFour/renderer.py
textarena/envs/Countdown/env.py
textarena/envs/Coup/base_coup_prompts.py
textarena/envs/Coup/coup_types.py
textarena/envs/Coup/env.py
textarena/envs/Crosswords/__init__.py
textarena/envs/Crosswords/env.py
textarena/envs/Crosswords/renderer.py
textarena/envs/Crosswords/words_clues.jsonl
textarena/envs/Crosswords/utils/words_clues_generator.py
textarena/envs/Crusade/__init__.py
textarena-0.7.4.dist-info/licenses/LICENSE
textarena-0.7.4.dist-info/METADATA
textarena-0.7.4.dist-info/WHEEL
textarena-0.7.4.dist-info/top_level.txt
textarena-0.7.4.dist-info/RECORD
