Metadata-Version: 2.4
Name: TextArena
Version: 0.7.4
Summary: A Collection of Competitive Text-Based Games for Language Model Evaluation and Reinforcement Learning
Author-email: Leon Guertler <Guertlerlo@cfar.a-star.edu.sg>
License: MIT
Project-URL: Homepage, https://www.textarena.ai/
Requires-Python: >=3.10
License-File: LICENSE
Requires-Dist: openai
Requires-Dist: rich
Requires-Dist: nltk
Requires-Dist: chess
Requires-Dist: python-dotenv
Requires-Dist: requests
Requires-Dist: websockets
Provides-Extra: all
Requires-Dist: sympy; extra == "all"
Requires-Dist: latex2sympy; extra == "all"
Requires-Dist: openai; extra == "all"
Requires-Dist: google-generativeai; extra == "all"
Requires-Dist: transformers; extra == "all"
Requires-Dist: cerebras-cloud-sdk; extra == "all"
Requires-Dist: boto3; extra == "all"
Requires-Dist: anthropic; extra == "all"
Dynamic: license-file
